bashate/__init__.py
bashate/__main__.py
bashate/bashate.py
bashate/messages.py
bashate/tests/__init__.py
bashate/tests/base.py
bashate/tests/test_bashate.py
bashate/tests/samples/.E005_excluded
bashate/tests/samples/E001_bad.sh
bashate/tests/samples/E002_bad.sh
bashate/tests/samples/E003_bad.sh
bashate/tests/samples/E003_good.sh
bashate/tests/samples/E004_bad.sh
bashate/tests/samples/E005_bad
bashate/tests/samples/E006_bad.sh
bashate/tests/samples/E006_bad_custom_length.sh
bashate/tests/samples/E006_good.sh
bashate/tests/samples/E010_bad.sh
bashate/tests/samples/E010_good.sh
bashate/tests/samples/E011_bad.sh
bashate/tests/samples/E011_good.sh
bashate/tests/samples/E012_bad.sh
bashate/tests/samples/E040_syntax_error.sh
bashate/tests/samples/E041_bad.sh
bashate/tests/samples/E042_bad.sh
bashate/tests/samples/E043_bad.sh
bashate/tests/samples/E044_bad.sh
bashate/tests/samples/comments.sh
bashate/tests/samples/for_loops.sh
bashate/tests/samples/heredoc_ignore.sh
bashate/tests/samples/legacy_sample.sh
bashate-2.1.0.dist-info/AUTHORS
bashate-2.1.0.dist-info/LICENSE
bashate-2.1.0.dist-info/METADATA
bashate-2.1.0.dist-info/WHEEL
bashate-2.1.0.dist-info/entry_points.txt
bashate-2.1.0.dist-info/pbr.json
bashate-2.1.0.dist-info/top_level.txt
bashate-2.1.0.dist-info/RECORD
